micropython_lis2mdl/__init__.py
micropython_lis2mdl/i2c_helpers.py
micropython_lis2mdl/lis2mdl.py
micropython_lis2mdl-0.1.0.dist-info/LICENSE
micropython_lis2mdl-0.1.0.dist-info/METADATA
micropython_lis2mdl-0.1.0.dist-info/WHEEL
micropython_lis2mdl-0.1.0.dist-info/top_level.txt
micropython_lis2mdl-0.1.0.dist-info/RECORD
