Metadata-Version: 2.1
Name: micropython-lis2mdl
Version: 0.1.0
Summary: MicroPython Driver for the ST LIS2MDL Magnetometer sensor
Author-email: JDM <xxyx@mailmeto.mozmail.com>
License: MIT
Project-URL: Homepage, https://github.com/jposada202020/MicroPython_LIS2MDL
Keywords: sensor,micropython,lis2mdl,micropython,sensor,driver,lis2mdl,st,magnetic,magnetometer
Classifier: Intended Audience :: Developers
Classifier: Topic :: Software Development :: Libraries
Classifier: Topic :: Software Development :: Embedded Systems
Classifier: Topic :: System :: Hardware
Classifier: License :: OSI Approved :: MIT License
Classifier: Programming Language :: Python :: Implementation :: MicroPython
License-File: LICENSE
